{"cameraMode":{"drawMode":0,"name":"Shaded","section":"Shading Mode"},"sceneLighting":false,"audioPlay":false,"sceneViewState":{"m_AlwaysRefresh":false,"showFog":true,"showSkybox":false,"showFlares":true,"showImageEffects":true,"showParticleSystems":true,"showVisualEffectGraphs":true,"m_FxEnabled":true},"in2DMode":false,"pivot":{"x":-32.63999557495117,"y":13.349640846252442,"z":-9.687453269958496},"rotation":{"x":0.16825832426548005,"y":0.43668344616889956,"z":-0.08296524733304978,"w":0.8799526691436768},"size":12.12435531616211,"orthographic":false}