{"cameraMode":{"drawMode":0,"name":"Shaded","section":"Shading Mode"},"sceneLighting":false,"audioPlay":false,"sceneViewState":{"m_AlwaysRefresh":false,"showFog":true,"showSkybox":false,"showFlares":true,"showImageEffects":true,"showParticleSystems":true,"showVisualEffectGraphs":true,"m_FxEnabled":true},"in2DMode":false,"pivot":{"x":-13.87653923034668,"y":2.5878067016601564,"z":0.3149658441543579},"rotation":{"x":0.21875998377799989,"y":0.6440821886062622,"z":-0.20000283420085908,"w":0.705325186252594},"size":0.4435184895992279,"orthographic":false}